<?xml version="1.0" ?>
<!-- Our to do list data -->
<UI>
	<Font Name="Data\simsun.ttc" Width="14" Height="14" />
		
	<Panel Name="MenuGuildAimEdit" X="200" Y="100"  Left="874"
		Top="4" Right="1143" Bottom="323" Hide="0" Image="Data\interface0035_Guild2.tga" 
		Drag="1" DragLeft="0" DragTop="0" DragRight="269" DragBottom="319" LuaRButtonUp="CloseGuildAimPanel" DetectImage = "1">
		
		<Button Name="GuildClose" Image="Data\interface0035_Guild2.tga" X="236" Y="8" LuaLButtonUp="CloseGuildAimPanel">
			<ButtonRect State="0" Left="590" Top="14" Right="612" Bottom="30" />	
			<ButtonRect State="1" Left="615" Top="14" Right="638" Bottom="30" />
			<ButtonRect State="2" Left="640" Top="14" Right="662" Bottom="30" />
			<ButtonRect State="3" Left="640" Top="14" Right="662" Bottom="30" />
			<ButtonRect State="4" Left="640" Top="14" Right="662" Bottom="30" />
		</Button>
		
		<!--
		<EditBox  Expand="1" Name="MenuGuildAimEdit" X="17" Y="44"  Row="1" Column="15" EdgeCode="LIGHT" FontColor="FFFFFFFF"
			ShadowColor="FF000000" LinePitch="10" Limit="100" Width="240" Height="160" ></EditBox>
		-->
			
		<ChatPanel Name="MenuGuildAimEditLine" Edit="1" LinePitch="10" X="17" Y="44" Width="240" Height="220" ContinueRun="0" EdgeCode="LIGHT"
			MaxLine="9"
			FontColor="FFFFFFFF" ShadowColor="FF000000" FillColor="7F0000FF" DisableScroll="1" Limit="100" UseEnter="1"
			>
		</ChatPanel>
		
		<Button Name="MenuGuildAimOK" Image="Data\interface0035_Guild2.tga" X="10" Y="270" LuaLButtonUp="ConfirmGuildAimChange" >
			<ButtonRect State="0" Left="387" Top="943" Right="481" Bottom="966" />
			<ButtonRect State="1" Left="483" Top="943" Right="577" Bottom="966" />
			<ButtonRect State="2" Left="579" Top="943" Right="673" Bottom="966" />
		</Button>
		
		<Button Name="MenuGuildAimCancel" Image="Data\interface0035_Guild2.tga" X="110" Y="270" LuaLButtonUp="CloseGuildAimPanel" >
			<ButtonRect State="0" Left="387" Top="971" Right="481" Bottom="994" />
			<ButtonRect State="1" Left="483" Top="971" Right="577" Bottom="994" />
			<ButtonRect State="2" Left="579" Top="971" Right="673" Bottom="994" />
		</Button>
	</Panel>
</UI>
